polls/__init__.py
polls/apps.py
polls/models.py
polls/test_models.py
polls/templates/polls/detail.html
polls/templates/polls/index.html
polls/templates/polls/results.html
warise_polls-0.0.2.dist-info/METADATA
warise_polls-0.0.2.dist-info/WHEEL
warise_polls-0.0.2.dist-info/licenses/LICENSE.txt
warise_polls-0.0.2.dist-info/RECORD
