Metadata-Version: 2.1
Name: warise-polls
Version: 0.0.2
Summary: polls on wagtail
Project-URL: Documentation, https://github.com/unknown/Appのパッケージ名#readme
Project-URL: Issues, https://github.com/unknown/Appのパッケージ名/issues
Project-URL: Source, https://github.com/unknown/Appのパッケージ名
Author-email: You are name <example@gmail.com>
License-Expression: MIT
License-File: LICENSE.txt
Classifier: Development Status :: 4 - Beta
Classifier: Environment :: Web Environment
Classifier: Framework :: Django
Classifier: Framework :: Wagtail
Classifier: Intended Audience :: Developers
Classifier: Programming Language :: Python
Classifier: Programming Language :: Python :: 3.7
Classifier: Programming Language :: Python :: Implementation :: CPython
Classifier: Programming Language :: Python :: Implementation :: PyPy
Requires-Python: >=3.7
Requires-Dist: wagtail==5.0.5
